{
  "meta": {
    "source": "https://github.com/sentomk/patternia",
    "package": "sentomk/patternia",
    "tag_filter": "^v\\d+\\.\\d+(\\.\\d+)?$",
    "date": "2026-05-04T13:58:44Z",
    "target": "",
    "description": "Providing pattern matching for modern c++."
  },
  "version": "0.9.3",
  "method": "fetch_content",
  "url": "https://github.com/sentomk/patternia/archive/refs/tags/v{{version}}.zip",
  "url_hash": "SHA256=d674774dfe6d84f808ca66030570a8f7ea49803613105fae651201e3042eccae",
  "update_disconnected": true,
  "options": {
    "PTN_INSTALL": "OFF",
    "PTN_BUILD_TESTS": "OFF",
    "PTN_BUILD_BENCHMARKS": "OFF",
    "PTN_BUILD_SAMPLES": "OFF",
    "PTN_DEV_INDEX": "ON",
    "PTN_SKIP_COMPILER_CHECK": "OFF"
  }
}